rote/__init__.py
rote/rote.py
rote-0.0.1.dist-info/DESCRIPTION.rst
rote-0.0.1.dist-info/METADATA
rote-0.0.1.dist-info/RECORD
rote-0.0.1.dist-info/WHEEL
rote-0.0.1.dist-info/metadata.json
rote-0.0.1.dist-info/top_level.txt
