Metadata-Version: 2.0
Name: rote
Version: 0.0.1
Summary: A tiny python library for making human-in-the-loop terminal apps
Home-page: http://github.com/j2kun/rote
Author: Jeremy Kun
Author-email: mathintersectprogramming@gmail.com
License: MIT
Keywords: rote human labeling
Platform: UNKNOWN
Classifier: Development Status :: 3 - Alpha
Classifier: Intended Audience :: Developers
Classifier: License :: OSI Approved :: MIT License
Classifier: Programming Language :: Python :: 3
